honors_board_extractor/__init__.py
honors_board_extractor/boards/__init__.py
honors_board_extractor/boards/assignments_query.py
honors_board_extractor/boards/dump.py
honors_board_extractor/boards/filter.py
honors_board_extractor/boards/map.py
honors_board_extractor/boards/pipeline.py
honors_board_extractor/boards/query.py
honors_board_extractor/boards/region_query.py
honors_board_extractor/boards/session.py
honors_board_extractor/charts/__init__.py
honors_board_extractor/charts/honors_chart_fetcher.py
honors_board_extractor/config/__init__.py
honors_board_extractor/config/config.py
honors_board_extractor/config/constants.py
honors_board_extractor/scripts/__init__.py
honors_board_extractor/scripts/cli.py
honors_board_extractor-1.1.5.dist-info/entry_points.txt
honors_board_extractor-1.1.5.dist-info/WHEEL
honors_board_extractor-1.1.5.dist-info/METADATA
honors_board_extractor-1.1.5.dist-info/RECORD
